LICENSE
README.md
pyproject.toml
easybuild/llm/__init__.py
easybuild_llm.egg-info/PKG-INFO
easybuild_llm.egg-info/SOURCES.txt
easybuild_llm.egg-info/dependency_links.txt
easybuild_llm.egg-info/requires.txt
easybuild_llm.egg-info/top_level.txt