Metadata-Version: 2.4
Name: easybuild-llm
Version: 0.1.0
Summary: Integration of EasyBuild with LLMs (coming soon)
Author-email: Kenneth Hoste <kenneth.hoste@ugent.be>
License-Expression: GPL-2.0-only
Project-URL: Repository, https://github.com/boegel/easybuild-llm
Project-URL: Changelog, https://github.com/boegel/easybuild-llm/blob/master/CHANGELOG.md
Classifier: Development Status :: 3 - Alpha
Classifier: Intended Audience :: Developers
Classifier: Topic :: Software Development :: Build Tools
Classifier: Programming Language :: Python :: 3
Classifier: Programming Language :: Python :: 3.9
Classifier: Programming Language :: Python :: 3.10
Classifier: Programming Language :: Python :: 3.11
Classifier: Programming Language :: Python :: 3.12
Classifier: Programming Language :: Python :: 3.13
Requires-Python: >=3.9
License-File: LICENSE
Requires-Dist: easybuild-framework
Dynamic: license-file
